setup.py
dsndrg_probability/Binomialdistribution.py
dsndrg_probability/Gaussiandistribution.py
dsndrg_probability/Generaldistribution.py
dsndrg_probability/__init__.py
dsndrg_probability.egg-info/PKG-INFO
dsndrg_probability.egg-info/SOURCES.txt
dsndrg_probability.egg-info/dependency_links.txt
dsndrg_probability.egg-info/not-zip-safe
dsndrg_probability.egg-info/top_level.txt