Metadata-Version: 2.1
Name: dsndrg-probability
Version: 1.0
Summary: Gaussian and Binomial distributions
Author: Rafael Gonzaga
Author-email: ralozaga@gmail.com
